py.typed
codat_sync_for_payables_version_1/__init__.py
codat_sync_for_payables_version_1/_hooks/__init__.py
codat_sync_for_payables_version_1/_hooks/registration.py
codat_sync_for_payables_version_1/_hooks/sdkhooks.py
codat_sync_for_payables_version_1/_hooks/types.py
codat_sync_for_payables_version_1/_version.py
codat_sync_for_payables_version_1/accounts.py
codat_sync_for_payables_version_1/bank_accounts.py
codat_sync_for_payables_version_1/basesdk.py
codat_sync_for_payables_version_1/bill_credit_notes.py
codat_sync_for_payables_version_1/bill_payments.py
codat_sync_for_payables_version_1/bills.py
codat_sync_for_payables_version_1/companies.py
codat_sync_for_payables_version_1/company_info.py
codat_sync_for_payables_version_1/connections.py
codat_sync_for_payables_version_1/httpclient.py
codat_sync_for_payables_version_1/journal_entries.py
codat_sync_for_payables_version_1/journals.py
codat_sync_for_payables_version_1/manage_data.py
codat_sync_for_payables_version_1/models/errors/__init__.py
codat_sync_for_payables_version_1/models/errors/errormessage.py
codat_sync_for_payables_version_1/models/errors/sdkerror.py
codat_sync_for_payables_version_1/models/operations/__init__.py
codat_sync_for_payables_version_1/models/operations/create_account.py
codat_sync_for_payables_version_1/models/operations/create_bank_account.py
codat_sync_for_payables_version_1/models/operations/create_bill.py
codat_sync_for_payables_version_1/models/operations/create_bill_credit_note.py
codat_sync_for_payables_version_1/models/operations/create_bill_payment.py
codat_sync_for_payables_version_1/models/operations/create_connection.py
codat_sync_for_payables_version_1/models/operations/create_journal.py
codat_sync_for_payables_version_1/models/operations/create_journal_entry.py
codat_sync_for_payables_version_1/models/operations/create_supplier.py
codat_sync_for_payables_version_1/models/operations/delete_bill.py
codat_sync_for_payables_version_1/models/operations/delete_bill_attachment.py
codat_sync_for_payables_version_1-3.2.1.dist-info/METADATA
codat_sync_for_payables_version_1-3.2.1.dist-info/WHEEL
codat_sync_for_payables_version_1-3.2.1.dist-info/RECORD
